ripple/__init__.py
ripple/core/__init__.py
ripple/core/db.py
ripple/core/meta.py
ripple/core/persistance.py
ripple/core/transaction.py
ripple/extra/__init__.py
ripple/extra/compression.py
ripple/extra/encryption.py
rippledb-0.0.1.dist-info/LICENSE
rippledb-0.0.1.dist-info/METADATA
rippledb-0.0.1.dist-info/WHEEL
rippledb-0.0.1.dist-info/top_level.txt
rippledb-0.0.1.dist-info/RECORD
