Metadata-Version: 2.1
Name: rippledb
Version: 0.0.1
Summary: This project is a simplified in-memory database inspired by redis
Home-page: https://github.com/dcambur/Ripple
Author: Cambur Dumitru
Author-email: dcambur@gmail.com
Classifier: Programming Language :: Python :: 3
Classifier: License :: OSI Approved :: MIT License
Classifier: Operating System :: OS Independent
Requires-Python: >=3.10
License-File: LICENSE
